thetakde/DCT.py
thetakde/__init__.py
thetakde/test_kde.py
thetakde/thetakde.py
thetakde-0.3.4.dist-info/licenses/LICENSE
thetakde-0.3.4.dist-info/METADATA
thetakde-0.3.4.dist-info/WHEEL
thetakde-0.3.4.dist-info/top_level.txt
thetakde-0.3.4.dist-info/RECORD
