Metadata-Version: 2.4
Name: thetakde
Version: 0.3.4
Summary: A package for the theta kernel density estimator
Home-page: https://github.com/DSML-book/ThetaKDE
Author: DSML-book
Author-email: kroese@maths.uq.edu.au
Classifier: Programming Language :: Python :: 3
Classifier: License :: OSI Approved :: MIT License
Classifier: Operating System :: OS Independent
Requires-Python: >=3.6
License-File: LICENSE
Requires-Dist: numpy
Requires-Dist: scipy
Requires-Dist: matplotlib
Dynamic: author
Dynamic: author-email
Dynamic: classifier
Dynamic: description
Dynamic: description-content-type
Dynamic: home-page
Dynamic: license-file
Dynamic: requires-dist
Dynamic: requires-python
Dynamic: summary
